{
  "gitSyncId": "6a4d033ae3824d264e76aad9_81c20ab5-5257-412b-880a-46d7c67dbc64",
  "id": "Nabory_Auth.extendSession",
  "pluginId": "js-plugin",
  "pluginType": "JS",
  "unpublishedAction": {
    "actionConfiguration": {
      "encodeParamsToggle": true,
      "jsArguments": [],
      "paginationType": "NONE",
      "timeoutInMillisecond": 10000
    },
    "collectionId": "Nabory_Auth",
    "confirmBeforeExecute": false,
    "datasource": {
      "isAutoGenerated": false,
      "name": "UNUSED_DATASOURCE",
      "pluginId": "js-plugin"
    },
    "dynamicBindingPathList": [
      {
        "key": "body"
      }
    ],
    "fullyQualifiedName": "Auth.extendSession",
    "name": "extendSession",
    "pageId": "Nabory",
    "runBehaviour": "MANUAL",
    "userSetOnLoad": false
  }
}