{
  "gitSyncId": "6a2fb7abb910071184e58185_5faab9e7-9be5-458e-82d1-c1f5da76cc1c",
  "id": "Eksperci_eksperciKategorie",
  "pluginId": "postgres-plugin",
  "pluginType": "DB",
  "unpublishedAction": {
    "actionConfiguration": {
      "body": "SELECT *\nFROM (\n    SELECT DISTINCT ON (eksperci.id)\n        eksperci.id AS ekspert_id,\n        dziedziny.id AS dziedzina_id,\n        kategorie_dziedziny.kategorie_id AS kategoria_id,\n        NULL::integer AS obszar_id,\n        eksperci.nazwisko,\n        eksperci.email,\n        eksperci.telefon1,\n        eksperci.umowa\n    FROM eksperci\n    INNER JOIN wykaz_ekspertow\n        ON eksperci.id = wykaz_ekspertow.eksperci_id\n    INNER JOIN dziedziny\n        ON dziedziny.id = wykaz_ekspertow.dziedziny_id\n    INNER JOIN kategorie_dziedziny\n        ON dziedziny.id = kategorie_dziedziny.dziedziny_id\n    WHERE\n        kategorie_dziedziny.kategorie_id = ANY(\n            string_to_array(\n                '{{ SelectWyszukaj.selectedOptionValues.join(\",\") }}',\n                ','\n            )::integer[]\n        )\n    ORDER BY\n        eksperci.id,\n        eksperci.nazwisko\n) wynik\nORDER BY\n    nazwisko COLLATE \"pl-x-icu\";",
      "encodeParamsToggle": true,
      "paginationType": "NONE",
      "pluginSpecifiedTemplates": [
        {
          "value": true
        }
      ],
      "timeoutInMillisecond": 10000
    },
    "confirmBeforeExecute": false,
    "datasource": {
      "id": "Supabase",
      "isAutoGenerated": false,
      "name": "Supabase",
      "pluginId": "postgres-plugin"
    },
    "dynamicBindingPathList": [
      {
        "key": "body"
      }
    ],
    "name": "eksperciKategorie",
    "pageId": "Eksperci",
    "runBehaviour": "AUTOMATIC",
    "userSetOnLoad": false
  }
}